{
    "swagger": "2.0",
    "info": {
        "description": "User Service Api.",
        "title": "User Service Api",
        "contact": {
            "name": "Reoden",
            "url": "https://github.com/Reoden"
        },
        "version": "1.0"
    },
    "paths": {
        "/api/v1/user": {
            "post": {
                "description": "Create new user item",
                "consumes": [
                    "application/json"
                ],
                "produces": [
                    "application/json"
                ],
                "tags": [
                    "User"
                ],
                "summary": "Create user",
                "parameters": [
                    {
                        "description": "User data",
                        "name": "CreateUserRequestDto",
                        "in": "body",
                        "required": true,
                        "schema": {
                            "$ref": "#/definitions/dtos.CreateUserRequestDto"
                        }
                    }
                ],
                "responses": {
                    "201": {
                        "description": "Created",
                        "schema": {
                            "$ref": "#/definitions/dtos.CreateUserResponseDto"
                        }
                    }
                }
            }
        }
    },
    "definitions": {
        "dtos.CreateUserRequestDto": {
            "type": "object",
            "properties": {
                "invite_code": {
                    "type": "string"
                },
                "phone": {
                    "type": "string"
                }
            }
        },
        "dtos.CreateUserResponseDto": {
            "type": "object",
            "properties": {
                "userID": {
                    "type": "string"
                }
            }
        }
    }
}